LICENSE
MANIFEST.in
README.md
setup.py
onecloud/__init__.py
onecloud/api.py
onecloud.egg-info/PKG-INFO
onecloud.egg-info/SOURCES.txt
onecloud.egg-info/dependency_links.txt
onecloud.egg-info/requires.txt
onecloud.egg-info/top_level.txt